food_waste_predictor.py
food_waste_predictor-0.13.dist-info/METADATA
food_waste_predictor-0.13.dist-info/WHEEL
food_waste_predictor-0.13.dist-info/entry_points.txt
food_waste_predictor-0.13.dist-info/top_level.txt
food_waste_predictor-0.13.dist-info/RECORD
